README.rst
setup.py
pyecowitt/__init__.py
pyecowitt/__main__.py
pyecowitt/ecowitt.py
pyecowitt/fake_client.py
pyecowitt/sensor_map.py
pyecowitt.egg-info/PKG-INFO
pyecowitt.egg-info/SOURCES.txt
pyecowitt.egg-info/dependency_links.txt
pyecowitt.egg-info/not-zip-safe
pyecowitt.egg-info/requires.txt
pyecowitt.egg-info/top_level.txt