Metadata-Version: 1.1
Name: pyecowitt
Version: 0.21
Summary: Module to communicate with the Ecowitt procotol
Home-page: https://github.com/garbled1/pyecowitt
Author: Tim Rightnour
Author-email: root@garbled.net
License: Apache 2.0
Platform: UNKNOWN
Classifier: Development Status :: 4 - Beta
Classifier: Intended Audience :: Developers
Classifier: License :: OSI Approved :: Apache Software License
Classifier: Programming Language :: Python :: 3 :: Only
Classifier: Topic :: Software Development :: Libraries :: Python Modules
